vegmod/__init__.py
vegmod/__main__.py
vegmod/base.py
vegmod/cache.py
vegmod/cli.py
vegmod/ingress.py
vegmod/serializer.py
vegmod/utils.py
vegmod/pycall/__init__.py
vegmod-1.0.27.dist-info/LICENSE
vegmod-1.0.27.dist-info/METADATA
vegmod-1.0.27.dist-info/WHEEL
vegmod-1.0.27.dist-info/entry_points.txt
vegmod-1.0.27.dist-info/top_level.txt
vegmod-1.0.27.dist-info/RECORD
